pysizing/__init__.py
pysizing/openmdao_generator/GUI_notebook.py
pysizing/openmdao_generator/Ipyvuetify GUI.ipynb
pysizing/openmdao_generator/__init__.py
pysizing/openmdao_generator/component_parse.py
pysizing/openmdao_generator/component_string.py
pysizing/openmdao_generator/delete.py
pysizing/openmdao_generator/derivative.py
pysizing/openmdao_generator/global_filegen.py
pysizing/openmdao_generator/global_string_gen.py
pysizing/openmdao_generator/group_parse.py
pysizing/openmdao_generator/group_string.py
pysizing/openmdao_generator/higher_parse.py
pysizing/openmdao_generator/n2_execute.py
pysizing/openmdao_generator/n2_globals.py
pysizing/openmdao_generator/parse_pack.py
pysizing/openmdao_generator/parse_values.py
pysizing/openmdao_generator/variable_data/variable_data.txt
pysizing/openmdao_generator/variable_rec_main.py
pysizing/openmdao_generator/variable_recognition.py
pysizing-0.1.1a0.dist-info/WHEEL
pysizing-0.1.1a0.dist-info/METADATA
pysizing-0.1.1a0.dist-info/RECORD
