Metadata-Version: 2.1
Name: pysizing
Version: 0.1.1a0
Summary: An open source framework for the sizing of technological systems
Home-page: https://github.com/SizingLab/pysizing
License: MIT
Keywords: sizing,optimization
Author: Scott DELBECQ
Author-email: scott.delbecq@isae-supaero.fr
Requires-Python: >=3.7,<4.0
Classifier: Environment :: Console
Classifier: Intended Audience :: Education
Classifier: Intended Audience :: Science/Research
Classifier: License :: OSI Approved :: MIT License
Classifier: Natural Language :: English
Classifier: Operating System :: OS Independent
Classifier: Programming Language :: Python :: 3
Classifier: Programming Language :: Python :: 3.10
Classifier: Programming Language :: Python :: 3.7
Classifier: Programming Language :: Python :: 3.8
Classifier: Programming Language :: Python :: 3.9
Classifier: Topic :: Scientific/Engineering :: Physics
Requires-Dist: black[jupyter] (==21.9b0)
Requires-Dist: ipysheet (>=0.5.0,<1)
Requires-Dist: ipyvuetify (>=1.7.1,<2.0.0)
Requires-Dist: ipywidgets (>=7.5.0,<8.0.0)
Requires-Dist: jupyter-client (!=7.0.0,!=7.0.1,!=7.0.2,!=7.0.3,!=7.0.4,!=7.0.5)
Requires-Dist: jupyterlab (>=3.0.18,<4.0.0)
Requires-Dist: numpy (>=1.17.3,<2.0.0)
Requires-Dist: openmdao (>=3.10,<4.0)
Requires-Dist: pandas (>=1.1.0,<2.0.0)
Requires-Dist: plotly (>=5.0.0,<6.0.0)
Requires-Dist: scipy (>=1.4.1,<2.0.0)
Requires-Dist: sympy
